signature_classifier/__init__.py
signature_classifier/main.py
Signature_Classifier-1.0.1.dist-info/LICENSE
Signature_Classifier-1.0.1.dist-info/METADATA
Signature_Classifier-1.0.1.dist-info/WHEEL
Signature_Classifier-1.0.1.dist-info/top_level.txt
Signature_Classifier-1.0.1.dist-info/RECORD
