Metadata-Version: 2.1
Name: Signature-Classifier
Version: 1.0.1
Summary: A package for signature classification with HOG features and KNN classifier, also for forg signatures detection
Home-page: https://github.com/Mercurlc/Signature-Classifier
Author: Mercurlc
Author-email: alexanderarefievrus@gmail.com
Project-URL: Source code, https://github.com/Mercurlc/Signature-Classifier
Project-URL: Documentation, https://signature-classifier.readthedocs.io/en/latest/
Project-URL: Example usage, https://github.com/Mercurlc/Signature-Classifier/blob/main/example-usage/example.py
Classifier: Programming Language :: Python :: 3
Classifier: License :: OSI Approved :: MIT License
Classifier: Operating System :: OS Independent
Requires-Python: >=3.11
License-File: LICENSE
Requires-Dist: matplotlib
Requires-Dist: numpy
Requires-Dist: optuna
Requires-Dist: pandas
Requires-Dist: scikit-image
Requires-Dist: scikit-learn
Requires-Dist: seaborn
Requires-Dist: sphinx
Requires-Dist: sphinx-autobuild
Requires-Dist: sphinx-rtd-theme
